MANIFEST.in
README.md
setup.py
flask_macros/__init__.py
flask_macros.egg-info/PKG-INFO
flask_macros.egg-info/SOURCES.txt
flask_macros.egg-info/dependency_links.txt
flask_macros.egg-info/not-zip-safe
flask_macros.egg-info/requires.txt
flask_macros.egg-info/top_level.txt
flask_macros/templates/macros/buttons.html
flask_macros/templates/macros/cols.html
flask_macros/templates/macros/forms.html
flask_macros/templates/macros/icons.html
flask_macros/templates/macros/pagination.html