Metadata-Version: 1.0
Name: flask-macros
Version: 0.1.5
Summary: macros for flask projects
Home-page: UNKNOWN
Author: Kyle Roux
Author-email: kyle@level2designs.com
License: UNKNOWN
Platform: UNKNOWN
